README.md
setup.py
lenluhub_utils/__init__.py
lenluhub_utils.egg-info/PKG-INFO
lenluhub_utils.egg-info/SOURCES.txt
lenluhub_utils.egg-info/dependency_links.txt
lenluhub_utils.egg-info/requires.txt
lenluhub_utils.egg-info/top_level.txt
lenluhub_utils/ceph_util/__init__.py
lenluhub_utils/ceph_util/ceph_client.py
lenluhub_utils/health_check/__init__.py
lenluhub_utils/health_check/moli_health_check.py
lenluhub_utils/health_check/moli_health_check_handler.py